.gitignore
.pre-commit-config.yaml
LICENSE
MANIFEST.in
Makefile
README.md
dev-requirements.txt
pyproject.toml
requirements.txt
setup.cfg
setup.py
.github/workflows/ci.yml
fbgbp/__init__.py
fbgbp/binary_belief_propagation.cpp
fbgbp/binary_belief_propagation.pxd
fbgbp/binary_belief_propagation.pyx
fbgbp/binary_grid_belief_propagation.cpp
fbgbp/binary_grid_belief_propagation.pyx
fbgbp/errors.py
fbgbp.egg-info/PKG-INFO
fbgbp.egg-info/SOURCES.txt
fbgbp.egg-info/dependency_links.txt
fbgbp.egg-info/not-zip-safe
fbgbp.egg-info/requires.txt
fbgbp.egg-info/top_level.txt
fbgbp/__pycache__/__init__.cpython-38.pyc
fbgbp/__pycache__/errors.cpython-38.pyc
fbgbp/src/binary_belief_propagation.cpp
fbgbp/src/binary_belief_propagation.hpp
fbgbp/src/parallel_for.hpp
fbgbp/wrappers/__init__.py
fbgbp/wrappers/binary_belief_propagation.pxd
tests/__init__.py
tests/mixins.py
tests/test_binary_belief_propagataion.py
tests/test_binary_grid_belief_propagataion.py
tests/fixtures/marginals.npy
tests/fixtures/n_neighbors.npy
tests/fixtures/neighbor_offsets.npy
tests/fixtures/neighbors.npy
tests/fixtures/potentials0.npy
tests/fixtures/potentials1.npy
tests/fixtures/shape.npy